fino/__init__.py
fino/console.py
fino/encryption.py
fino/ipfs.py
fino/main.py
fino/nostr.py
fino/utils.py
fino/commands/gen_key.py
fino/commands/receive.py
fino/commands/send.py
pyfino-0.3.0.dist-info/licenses/LICENSE
pyfino-0.3.0.dist-info/METADATA
pyfino-0.3.0.dist-info/WHEEL
pyfino-0.3.0.dist-info/entry_points.txt
pyfino-0.3.0.dist-info/top_level.txt
pyfino-0.3.0.dist-info/RECORD
