Metadata-Version: 2.4
Name: pyfino
Version: 0.3.0
Summary: Proof-of-Concept: Secure File Sharing via IPFS + Nostr DMs
Author: arnispen
License-Expression: MIT
Project-URL: Homepage, https://github.com/arnispen/pyfino
Project-URL: Repository, https://github.com/arnispen/pyfino
Project-URL: Issues, https://github.com/arnispen/pyfino/issues
Keywords: nostr,ipfs,encryption,file-sharing,proof-of-concept,innovation
Classifier: Development Status :: 4 - Beta
Classifier: Intended Audience :: Developers
Classifier: Programming Language :: Python :: 3
Classifier: Programming Language :: Python :: 3.8
Classifier: Programming Language :: Python :: 3.9
Classifier: Programming Language :: Python :: 3.10
Classifier: Programming Language :: Python :: 3.11
Classifier: Topic :: Communications :: File Sharing
Classifier: Topic :: Security :: Cryptography
Classifier: Topic :: Software Development :: Libraries :: Python Modules
Requires-Python: >=3.8
License-File: LICENSE
Requires-Dist: cryptography>=41.0.0
Requires-Dist: requests>=2.28.0
Requires-Dist: pynostr[websocket-client]>=0.0.20
Requires-Dist: typer>=0.9.0
Requires-Dist: python-dotenv>=1.0.0
Requires-Dist: websockets>=11.0.0
Requires-Dist: rich>=13.0.0
Provides-Extra: dev
Requires-Dist: ruff>=0.6.0; extra == "dev"
Requires-Dist: mypy>=1.0.0; extra == "dev"
Requires-Dist: types-requests>=2.31.0; extra == "dev"
Dynamic: license-file
